<?xml version="1.0" encoding="utf-8"?>
<odoo>
    <record id="brand_abarth" model="used.vehicle.model.brand">
        <field name="name">Abarth</field>
        <field name="image_128" type="base64" file="zillotech_vehicle_sale/static/img/brand_abarth-image.png"/>
    </record>
    <record id="brand_acura" model="used.vehicle.model.brand">
        <field name="name">Acura</field>
        <field name="image_128" type="base64" file="zillotech_vehicle_sale/static/img/brand_acura-image.png"/>
    </record>
    <record id="brand_alfa" model="used.vehicle.model.brand">
        <field name="name">Alfa</field>
        <field name="image_128" type="base64" file="zillotech_vehicle_sale/static/img/brand_alfa-image.png"/>
    </record>
    <record id="brand_audi" model="used.vehicle.model.brand">
        <field name="name">Audi</field>
        <field name="image_128" type="base64" file="zillotech_vehicle_sale/static/img/brand_audi-image.png"/>
    </record>
    <record id="brand_austin" model="used.vehicle.model.brand">
        <field name="name">Austin</field>
        <field name="image_128" type="base64" file="zillotech_vehicle_sale/static/img/brand_austin-image.png"/>
    </record>
    <record id="brand_bentley" model="used.vehicle.model.brand">
        <field name="name">Bentley</field>
        <field name="image_128" type="base64" file="zillotech_vehicle_sale/static/img/brand_bentley-image.png"/>
    </record>
    <record id="brand_bmw" model="used.vehicle.model.brand">
        <field name="name">Bmw</field>
        <field name="image_128" type="base64" file="zillotech_vehicle_sale/static/img/brand_bmw-image.png"/>
    </record>
    <record id="brand_bugatti" model="used.vehicle.model.brand">
        <field name="name">Bugatti</field>
        <field name="image_128" type="base64" file="zillotech_vehicle_sale/static/img/brand_bugatti-image.png"/>
    </record>
    <record id="brand_buick" model="used.vehicle.model.brand">
        <field name="name">Buick</field>
        <field name="image_128" type="base64" file="zillotech_vehicle_sale/static/img/brand_buick-image.png"/>
    </record>
    <record id="brand_byd" model="used.vehicle.model.brand">
        <field name="name">Byd</field>
        <field name="image_128" type="base64" file="zillotech_vehicle_sale/static/img/brand_byd-image.png"/>
    </record>
    <record id="brand_cadillac" model="used.vehicle.model.brand">
        <field name="name">Cadillac</field>
        <field name="image_128" type="base64" file="zillotech_vehicle_sale/static/img/brand_cadillac-image.png"/>
    </record>
    <record id="brand_chevrolet" model="used.vehicle.model.brand">
        <field name="name">Chevrolet</field>
        <field name="image_128" type="base64" file="zillotech_vehicle_sale/static/img/brand_chevrolet-image.png"/>
    </record>
    <record id="brand_chrysler" model="used.vehicle.model.brand">
        <field name="name">Chrysler</field>
        <field name="image_128" type="base64" file="zillotech_vehicle_sale/static/img/brand_chrysler-image.png"/>
    </record>
    <record id="brand_citroen" model="used.vehicle.model.brand">
        <field name="name">Citroen</field>
        <field name="image_128" type="base64" file="zillotech_vehicle_sale/static/img/brand_citroen-image.png"/>
    </record>
    <record id="brand_corre_la_licorne" model="used.vehicle.model.brand">
        <field name="name">Corre La Licorne</field>
        <field name="image_128" type="base64" file="zillotech_vehicle_sale/static/img/brand_corre-la-licorne-image.png"/>
    </record>
    <record id="brand_daewoo" model="used.vehicle.model.brand">
        <field name="name">Daewoo</field>
        <field name="image_128" type="base64" file="zillotech_vehicle_sale/static/img/brand_daewoo-image.png"/>
    </record>
    <record id="brand_dodge" model="used.vehicle.model.brand">
        <field name="name">Dodge</field>
        <field name="image_128" type="base64" file="zillotech_vehicle_sale/static/img/brand_dodge-image.png"/>
    </record>
    <record id="brand_ferrari" model="used.vehicle.model.brand">
        <field name="name">Ferrari</field>
        <field name="image_128" type="base64" file="zillotech_vehicle_sale/static/img/brand_ferrari-image.png"/>
    </record>
    <record id="brand_fiat" model="used.vehicle.model.brand">
        <field name="name">Fiat</field>
        <field name="image_128" type="base64" file="zillotech_vehicle_sale/static/img/brand_fiat-image.png"/>
    </record>
    <record id="brand_ford" model="used.vehicle.model.brand">
        <field name="name">Ford</field>
        <field name="image_128" type="base64" file="zillotech_vehicle_sale/static/img/brand_ford-image.png"/>
    </record>
    <record id="brand_holden" model="used.vehicle.model.brand">
        <field name="name">Holden</field>
        <field name="image_128" type="base64" file="zillotech_vehicle_sale/static/img/brand_holden-image.png"/>
    </record>
    <record id="brand_honda" model="used.vehicle.model.brand">
        <field name="name">Honda</field>
        <field name="image_128" type="base64" file="zillotech_vehicle_sale/static/img/brand_honda-image.png"/>
    </record>
    <record id="brand_hyundai" model="used.vehicle.model.brand">
        <field name="name">Hyundai</field>
        <field name="image_128" type="base64" file="zillotech_vehicle_sale/static/img/brand_hyundai-image.png"/>
    </record>
    <record id="brand_infiniti" model="used.vehicle.model.brand">
        <field name="name">Infiniti</field>
        <field name="image_128" type="base64" file="zillotech_vehicle_sale/static/img/brand_infiniti-image.png"/>
    </record>
    <record id="brand_isuzu" model="used.vehicle.model.brand">
        <field name="name">Isuzu</field>
        <field name="image_128" type="base64" file="zillotech_vehicle_sale/static/img/brand_isuzu-image.png"/>
    </record>
    <record id="brand_jaguar" model="used.vehicle.model.brand">
        <field name="name">Jaguar</field>
        <field name="image_128" type="base64" file="zillotech_vehicle_sale/static/img/brand_jaguar-image.png"/>
    </record>
    <record id="brand_jeep" model="used.vehicle.model.brand">
        <field name="name">Jeep</field>
        <field name="image_128" type="base64" file="zillotech_vehicle_sale/static/img/brand_jeep-image.png"/>
    </record>
    <record id="brand_kia" model="used.vehicle.model.brand">
        <field name="name">Kia</field>
        <field name="image_128" type="base64" file="zillotech_vehicle_sale/static/img/brand_kia-image.png"/>
    </record>
    <record id="brand_koenigsegg" model="used.vehicle.model.brand">
        <field name="name">Koenigsegg</field>
        <field name="image_128" type="base64" file="zillotech_vehicle_sale/static/img/brand_koenigsegg-image.png"/>
    </record>
    <record id="brand_lagonda" model="used.vehicle.model.brand">
        <field name="name">Lagonda</field>
        <field name="image_128" type="base64" file="zillotech_vehicle_sale/static/img/brand_lagonda-image.png"/>
    </record>
    <record id="brand_lamborghini" model="used.vehicle.model.brand">
        <field name="name">Lamborghini</field>
        <field name="image_128" type="base64" file="zillotech_vehicle_sale/static/img/brand_lamborghini-image.png"/>
    </record>
    <record id="brand_lancia" model="used.vehicle.model.brand">
        <field name="name">Lancia</field>
        <field name="image_128" type="base64" file="zillotech_vehicle_sale/static/img/brand_lancia-image.png"/>
    </record>
    <record id="brand_land_rover" model="used.vehicle.model.brand">
        <field name="name">Land Rover</field>
        <field name="image_128" type="base64" file="zillotech_vehicle_sale/static/img/brand_land-rover-image.png"/>
    </record>
    <record id="brand_lexus" model="used.vehicle.model.brand">
        <field name="name">Lexus</field>
        <field name="image_128" type="base64" file="zillotech_vehicle_sale/static/img/brand_lexus-image.png"/>
    </record>
    <record id="brand_lincoln" model="used.vehicle.model.brand">
        <field name="name">Lincoln</field>
        <field name="image_128" type="base64" file="zillotech_vehicle_sale/static/img/brand_lincoln-image.png"/>
    </record>
    <record id="brand_lotus" model="used.vehicle.model.brand">
        <field name="name">Lotus</field>
        <field name="image_128" type="base64" file="zillotech_vehicle_sale/static/img/brand_lotus-image.png"/>
    </record>
    <record id="brand_maserati" model="used.vehicle.model.brand">
        <field name="name">Maserati</field>
        <field name="image_128" type="base64" file="zillotech_vehicle_sale/static/img/brand_maserati-image.png"/>
    </record>
    <record id="brand_maybach" model="used.vehicle.model.brand">
        <field name="name">Maybach</field>
        <field name="image_128" type="base64" file="zillotech_vehicle_sale/static/img/brand_maybach-image.png"/>
    </record>
    <record id="brand_mazda" model="used.vehicle.model.brand">
        <field name="name">Mazda</field>
        <field name="image_128" type="base64" file="zillotech_vehicle_sale/static/img/brand_mazda-image.png"/>
    </record>
    <record id="brand_mercedes" model="used.vehicle.model.brand">
        <field name="name">Mercedes</field>
        <field name="image_128" type="base64" file="zillotech_vehicle_sale/static/img/brand_mercedes-image.png"/>
    </record>
    <record id="brand_mg" model="used.vehicle.model.brand">
        <field name="name">Mg</field>
        <field name="image_128" type="base64" file="zillotech_vehicle_sale/static/img/brand_mg-image.png"/>
    </record>
    <record id="brand_mini" model="used.vehicle.model.brand">
        <field name="name">Mini</field>
        <field name="image_128" type="base64" file="zillotech_vehicle_sale/static/img/brand_mini-image.png"/>
    </record>
    <record id="brand_mitsubishi" model="used.vehicle.model.brand">
        <field name="name">Mitsubishi</field>
        <field name="image_128" type="base64" file="zillotech_vehicle_sale/static/img/brand_mitsubishi-image.png"/>
    </record>
    <record id="brand_morgan" model="used.vehicle.model.brand">
        <field name="name">Morgan</field>
        <field name="image_128" type="base64" file="zillotech_vehicle_sale/static/img/brand_morgan-image.png"/>
    </record>
    <record id="brand_nissan" model="used.vehicle.model.brand">
        <field name="name">Nissan</field>
        <field name="image_128" type="base64" file="zillotech_vehicle_sale/static/img/brand_nissan-image.png"/>
    </record>
    <record id="brand_oldsmobile" model="used.vehicle.model.brand">
        <field name="name">Oldsmobile</field>
        <field name="image_128" type="base64" file="zillotech_vehicle_sale/static/img/brand_oldsmobile-image.png"/>
    </record>
    <record id="brand_opel" model="used.vehicle.model.brand">
        <field name="name">Opel</field>
        <field name="image_128" type="base64" file="zillotech_vehicle_sale/static/img/brand_opel-image.png"/>
    </record>
    <record id="brand_peugeot" model="used.vehicle.model.brand">
        <field name="name">Peugeot</field>
        <field name="image_128" type="base64" file="zillotech_vehicle_sale/static/img/brand_peugeot-image.png"/>
    </record>
    <record id="brand_pontiac" model="used.vehicle.model.brand">
        <field name="name">Pontiac</field>
        <field name="image_128" type="base64" file="zillotech_vehicle_sale/static/img/brand_pontiac-image.png"/>
    </record>
    <record id="brand_porsche" model="used.vehicle.model.brand">
        <field name="name">Porsche</field>
        <field name="image_128" type="base64" file="zillotech_vehicle_sale/static/img/brand_porsche-image.png"/>
    </record>
    <record id="brand_rambler" model="used.vehicle.model.brand">
        <field name="name">Rambler</field>
        <field name="image_128" type="base64" file="zillotech_vehicle_sale/static/img/brand_rambler-image.png"/>
    </record>
    <record id="brand_renault" model="used.vehicle.model.brand">
        <field name="name">Renault</field>
        <field name="image_128" type="base64" file="zillotech_vehicle_sale/static/img/brand_renault-image.png"/>
    </record>
    <record id="brand_rolls-royce" model="used.vehicle.model.brand">
        <field name="name">Rolls-Royce</field>
        <field name="image_128" type="base64" file="zillotech_vehicle_sale/static/img/brand_rolls-royce-image.png"/>
    </record>
    <record id="brand_saab" model="used.vehicle.model.brand">
        <field name="name">Saab</field>
        <field name="image_128" type="base64" file="zillotech_vehicle_sale/static/img/brand_saab-image.png"/>
    </record>
    <record id="brand_scion" model="used.vehicle.model.brand">
        <field name="name">Scion</field>
        <field name="image_128" type="base64" file="zillotech_vehicle_sale/static/img/brand_scion-image.png"/>
    </record>
    <record id="brand_skoda" model="used.vehicle.model.brand">
        <field name="name">Skoda</field>
        <field name="image_128" type="base64" file="zillotech_vehicle_sale/static/img/brand_skoda-image.png"/>
    </record>
    <record id="brand_smart" model="used.vehicle.model.brand">
        <field name="name">Smart</field>
        <field name="image_128" type="base64" file="zillotech_vehicle_sale/static/img/brand_smart-image.png"/>
    </record>
    <record id="brand_steyr" model="used.vehicle.model.brand">
        <field name="name">Steyr</field>
        <field name="image_128" type="base64" file="zillotech_vehicle_sale/static/img/brand_steyr-image.png"/>
    </record>
    <record id="brand_subaru" model="used.vehicle.model.brand">
        <field name="name">Subaru</field>
        <field name="image_128" type="base64" file="zillotech_vehicle_sale/static/img/brand_subaru-image.png"/>
    </record>
    <record id="brand_tesla_motors" model="used.vehicle.model.brand">
        <field name="name">Tesla Motors</field>
        <field name="image_128" type="base64" file="zillotech_vehicle_sale/static/img/brand_tesla-motors-image.png"/>
    </record>
    <record id="brand_toyota" model="used.vehicle.model.brand">
        <field name="name">Toyota</field>
        <field name="image_128" type="base64" file="zillotech_vehicle_sale/static/img/brand_toyota-image.png"/>
    </record>
    <record id="brand_trabant" model="used.vehicle.model.brand">
        <field name="name">Trabant</field>
        <field name="image_128" type="base64" file="zillotech_vehicle_sale/static/img/brand_trabant-image.png"/>
    </record>
    <record id="brand_volkswagen" model="used.vehicle.model.brand">
        <field name="name">Volkswagen</field>
        <field name="image_128" type="base64" file="zillotech_vehicle_sale/static/img/brand_volkswagen-image.png"/>
    </record>
    <record id="brand_volvo" model="used.vehicle.model.brand">
        <field name="name">Volvo</field>
        <field name="image_128" type="base64" file="zillotech_vehicle_sale/static/img/brand_volvo-image.png"/>
    </record>
    <record id="brand_willys" model="used.vehicle.model.brand">
        <field name="name">Willys</field>
        <field name="image_128" type="base64" file="zillotech_vehicle_sale/static/img/brand_willys-image.png"/>
    </record>
    <record id="brand_suzuki" model="used.vehicle.model.brand">
        <field name="name">Suzuki</field>
        <field name="image_128" type="base64" file="zillotech_vehicle_sale/static/img/brand_suzuki-image.png"/>
    </record>
    <record id="color_black" model="used.vehicle.exterior.color">
        <field name="exterior_color">Black</field>
    </record>
    <record id="color_blue" model="used.vehicle.exterior.color">
        <field name="exterior_color">Blue</field>
    </record>
    <record id="color_yellow" model="used.vehicle.exterior.color">
        <field name="exterior_color">Yellow</field>
    </record>
    <record id="color_green" model="used.vehicle.exterior.color">
        <field name="exterior_color">Green</field>
    </record>
    <record id="color_white" model="used.vehicle.exterior.color">
        <field name="exterior_color">White</field>
    </record>
    <record id="color_red" model="used.vehicle.exterior.color">
        <field name="exterior_color">Red</field>
    </record>
    <record id="used_color_black" model="used.vehicle.interior.color">
        <field name="interior_color">Black</field>
    </record>
    <record id="used_color_blue" model="used.vehicle.interior.color">
        <field name="interior_color">Blue</field>
    </record>
    <record id="used_color_yellow" model="used.vehicle.interior.color">
        <field name="interior_color">Yellow</field>
    </record>
    <record id="used_color_green" model="used.vehicle.interior.color">
        <field name="interior_color">Green</field>
    </record>
    <record id="used_color_white" model="used.vehicle.interior.color">
        <field name="interior_color">White</field>
    </record>
    <record id="used_color_red" model="used.vehicle.interior.color">
        <field name="interior_color">Red</field>
    </record>
</odoo>
